state_graph/__init__.py
state_graph/__main__.py
state_graph/edge.py
state_graph/graph.py
state_graph/node.py
state_graph/utils.py
state_graph-0.2.13.dist-info/METADATA
state_graph-0.2.13.dist-info/WHEEL
state_graph-0.2.13.dist-info/top_level.txt
state_graph-0.2.13.dist-info/RECORD
