Metadata-Version: 2.1
Name: state_graph
Version: 0.2.13
Requires-Dist: pydantic
Requires-Dist: networkx
Requires-Dist: beartype
Requires-Dist: rich
Requires-Dist: ipython
